README.md
setup.cfg
setup.py
cloudmersive_virus_api_client/__init__.py
cloudmersive_virus_api_client/api_client.py
cloudmersive_virus_api_client/configuration.py
cloudmersive_virus_api_client/rest.py
cloudmersive_virus_api_client.egg-info/PKG-INFO
cloudmersive_virus_api_client.egg-info/SOURCES.txt
cloudmersive_virus_api_client.egg-info/dependency_links.txt
cloudmersive_virus_api_client.egg-info/requires.txt
cloudmersive_virus_api_client.egg-info/top_level.txt
cloudmersive_virus_api_client/api/__init__.py
cloudmersive_virus_api_client/api/scan_api.py
cloudmersive_virus_api_client/api/scan_cloud_storage_api.py
cloudmersive_virus_api_client/models/__init__.py
cloudmersive_virus_api_client/models/additional_advanced_scan_information.py
cloudmersive_virus_api_client/models/cloud_storage_advanced_virus_scan_result.py
cloudmersive_virus_api_client/models/cloud_storage_virus_found.py
cloudmersive_virus_api_client/models/cloud_storage_virus_scan_result.py
cloudmersive_virus_api_client/models/virus_found.py
cloudmersive_virus_api_client/models/virus_scan_advanced_result.py
cloudmersive_virus_api_client/models/virus_scan_result.py
cloudmersive_virus_api_client/models/website_scan_request.py
cloudmersive_virus_api_client/models/website_scan_result.py
test/__init__.py
test/test_additional_advanced_scan_information.py
test/test_cloud_storage_advanced_virus_scan_result.py
test/test_cloud_storage_virus_found.py
test/test_cloud_storage_virus_scan_result.py
test/test_scan_api.py
test/test_scan_cloud_storage_api.py
test/test_virus_found.py
test/test_virus_scan_advanced_result.py
test/test_virus_scan_result.py
test/test_website_scan_request.py
test/test_website_scan_result.py