Metadata-Version: 2.1
Name: cloudmersive-virus-api-client
Version: 3.0.8
Summary: virusapi
Home-page: https://www.cloudmersive.com/virus-api
Author-email: 
License: UNKNOWN
Keywords: Swagger,virusapi
Platform: UNKNOWN
